donew/__init__.py
donew/install.py
donew/scripts/web/element_detection.js
donew/scripts/web/highlight_elements.js
donew/scripts/web/highlight_styles.css
donew/scripts/web/restore_text_markers.js
donew/scripts/web/text_markers.js
donew/see/__init__.py
donew/see/processors/__init__.py
donew/see/processors/web.py
donew-0.1.5.dist-info/LICENSE
donew-0.1.5.dist-info/METADATA
donew-0.1.5.dist-info/WHEEL
donew-0.1.5.dist-info/entry_points.txt
donew-0.1.5.dist-info/top_level.txt
donew-0.1.5.dist-info/RECORD
