Metadata-Version: 2.1
Name: donew
Version: 0.1.5
Summary: A Python package for web processing and vision tasks with browser automation capabilities
Author-email: Kenan Deniz <kenan@unrealists.com>
License: MIT
Keywords: web automation,vision,browser,playwright,image processing
Classifier: Development Status :: 3 - Alpha
Classifier: Intended Audience :: Developers
Classifier: License :: OSI Approved :: MIT License
Classifier: Programming Language :: Python :: 3
Classifier: Programming Language :: Python :: 3.8
Classifier: Programming Language :: Python :: 3.9
Classifier: Programming Language :: Python :: 3.10
Classifier: Programming Language :: Python :: 3.11
Classifier: Topic :: Software Development :: Libraries :: Python Modules
Classifier: Topic :: Internet :: WWW/HTTP :: Browsers
Classifier: Topic :: Scientific/Engineering :: Image Processing
Requires-Python: >=3.8
License-File: LICENSE
Requires-Dist: aiohttp>=3.9.1
Requires-Dist: playwright>=1.40.0
Requires-Dist: typing-extensions>=4.12.2
Requires-Dist: tabulate>=0.9.0
Provides-Extra: dev
Requires-Dist: pytest>=8.3.4; extra == "dev"
Requires-Dist: pytest-asyncio>=0.25.0; extra == "dev"
Requires-Dist: pytest-cov>=4.1.0; extra == "dev"
Requires-Dist: black>=23.10.0; extra == "dev"
Requires-Dist: isort>=5.3.2; extra == "dev"
Requires-Dist: mypy>=1.14.0; extra == "dev"
Requires-Dist: ruff>=0.8.4; extra == "dev"
